odoo8_addon_account_voucher_cash_basis-8.0.1.0.0.99.dev31-py2.7-nspkg.pth
odoo8_addon_account_voucher_cash_basis-8.0.1.0.0.99.dev31.dist-info/METADATA
odoo8_addon_account_voucher_cash_basis-8.0.1.0.0.99.dev31.dist-info/RECORD
odoo8_addon_account_voucher_cash_basis-8.0.1.0.0.99.dev31.dist-info/WHEEL
odoo8_addon_account_voucher_cash_basis-8.0.1.0.0.99.dev31.dist-info/namespace_packages.txt
odoo8_addon_account_voucher_cash_basis-8.0.1.0.0.99.dev31.dist-info/top_level.txt
odoo_addons/account_voucher_cash_basis/README.rst
odoo_addons/account_voucher_cash_basis/__init__.py
odoo_addons/account_voucher_cash_basis/__openerp__.py
odoo_addons/account_voucher_cash_basis/account_voucher.py
odoo_addons/account_voucher_cash_basis/company.py
odoo_addons/account_voucher_cash_basis/company_view.xml
odoo_addons/account_voucher_cash_basis/voucher_view.xml
odoo_addons/account_voucher_cash_basis/i18n/account_voucher_cash_basis.pot
odoo_addons/account_voucher_cash_basis/i18n/am.po
odoo_addons/account_voucher_cash_basis/i18n/ar.po
odoo_addons/account_voucher_cash_basis/i18n/ca.po
odoo_addons/account_voucher_cash_basis/i18n/da.po
odoo_addons/account_voucher_cash_basis/i18n/de.po
odoo_addons/account_voucher_cash_basis/i18n/el_GR.po
odoo_addons/account_voucher_cash_basis/i18n/es.po
odoo_addons/account_voucher_cash_basis/i18n/es_ES.po
odoo_addons/account_voucher_cash_basis/i18n/es_MX.po
odoo_addons/account_voucher_cash_basis/i18n/eu.po
odoo_addons/account_voucher_cash_basis/i18n/fi.po
odoo_addons/account_voucher_cash_basis/i18n/fr.po
odoo_addons/account_voucher_cash_basis/i18n/fr_CA.po
odoo_addons/account_voucher_cash_basis/i18n/fr_FR.po
odoo_addons/account_voucher_cash_basis/i18n/hr.po
odoo_addons/account_voucher_cash_basis/i18n/hr_HR.po
odoo_addons/account_voucher_cash_basis/i18n/it.po
odoo_addons/account_voucher_cash_basis/i18n/nb.po
odoo_addons/account_voucher_cash_basis/i18n/nb_NO.po
odoo_addons/account_voucher_cash_basis/i18n/nl.po
odoo_addons/account_voucher_cash_basis/i18n/nl_BE.po
odoo_addons/account_voucher_cash_basis/i18n/nl_NL.po
odoo_addons/account_voucher_cash_basis/i18n/pt_BR.po
odoo_addons/account_voucher_cash_basis/i18n/pt_PT.po
odoo_addons/account_voucher_cash_basis/i18n/ro.po
odoo_addons/account_voucher_cash_basis/i18n/sk.po
odoo_addons/account_voucher_cash_basis/i18n/sl.po
odoo_addons/account_voucher_cash_basis/i18n/tr.po
